aext_shared/__init__.py
aext_shared-0.0.1.dist-info/METADATA
aext_shared-0.0.1.dist-info/WHEEL
aext_shared-0.0.1.dist-info/RECORD
