Metadata-Version: 2.1
Name: aext-shared
Version: 0.0.1
Summary: The aext-shared component of anaconda-toolbox
License-Expression: BSD-3-Clause
